[
    {
        "profileId": "568594eerd",
        "studentName": "Jack",
        "imgSrc": ""
    },
    {
        "profileId": "12345eereds",
        "studentName": "NickleSon",
        "imgSrc": ""
    },
    {
        "profileId": "78773njkhcg",
        "studentName": "Jordan",
        "imgSrc": ""
    },
    {
        "profileId": "78773njkhcg",
        "studentName": "Dwayne smith",
        "imgSrc": ""
    },
    {
        "profileId": "568594eerd",
        "studentName": "Randy",
        "imgSrc": ""
    },
    {
        "profileId": "00564fgd",
        "studentName": "Brad",
        "imgSrc": ""
    },
    {
        "profileId": "78773njkhcg",
        "studentName": "Dwayne smith",
        "imgSrc": ""
    },
    {
        "profileId": "568594eerd",
        "studentName": "Will Smith",
        "imgSrc": ""
    },

    {
        "profileId": "568594eerd",
        "studentName": "Randy",
        "imgSrc": ""
    },
    {
        "profileId": "00564fgd",
        "studentName": "Brad",
        "imgSrc": ""
    }
]